hot_shelve/__init__.py
hot_shelve/flat_shelve.py
hot_shelve/hot_shelve.py
hot_shelve-0.1.2.dist-info/WHEEL
hot_shelve-0.1.2.dist-info/METADATA
hot_shelve-0.1.2.dist-info/RECORD
